pyrcbm/__init__.py
pyrcbm/csv2rcbm.py
pyrcbm/sin_rcbm.py
pyrcbm/ulog2rcbm.py
pyrcbm-0.3.2.dist-info/METADATA
pyrcbm-0.3.2.dist-info/WHEEL
pyrcbm-0.3.2.dist-info/entry_points.txt
pyrcbm-0.3.2.dist-info/top_level.txt
pyrcbm-0.3.2.dist-info/RECORD
