Metadata-Version: 2.1
Name: pyrcbm
Version: 0.3.2
Summary: RCbenchmark script generation tools
Home-page: https://github.com/lirc572/pyrcbm
Author: lirc572
Author-email: lirc572@gmail.com
License: UNKNOWN
Keywords: rcbenchmark,ulog
Platform: UNKNOWN
Classifier: Programming Language :: Python :: 3
Classifier: Programming Language :: Python :: 3.8
Classifier: Programming Language :: Python :: 3.9
Classifier: Programming Language :: Python :: 3.10
Requires-Python: >=3.8
Requires-Dist: pyulog (>=0.9.0)
